sftp_cloudfs-0.21.data/scripts/sftpcloudfs
sftpcloudfs/__init__.py
sftpcloudfs/constants.py
sftpcloudfs/main.py
sftpcloudfs/scp.py
sftpcloudfs/server.py
sftp_cloudfs-0.21.dist-info/COPYING
sftp_cloudfs-0.21.dist-info/METADATA
sftp_cloudfs-0.21.dist-info/WHEEL
sftp_cloudfs-0.21.dist-info/top_level.txt
sftp_cloudfs-0.21.dist-info/RECORD
