Metadata-Version: 2.1
Name: sftp-cloudfs
Version: 0.21
Summary: SFTP interface to OpenStack Object Storage (Swift)
Home-page: https://pypi.python.org/pypi/sftp-cloudfs/
Author: Nick Craig-Wood
Author-email: nick@memset.com
License: MIT
Platform: UNKNOWN
Classifier: Development Status :: 4 - Beta
Classifier: Environment :: Console
Classifier: Programming Language :: Python
Classifier: Operating System :: OS Independent
Classifier: Environment :: No Input/Output (Daemon)
Classifier: License :: OSI Approved :: MIT License
Requires-Dist: paramiko (>=1.7.6)
Requires-Dist: python-swiftclient (>=2.0.0)
Requires-Dist: python-daemon (>=1.5)
Requires-Dist: python-memcached (>=1.45)
Requires-Dist: ftp-cloudfs (>=0.35)
